setup.py
cypar/__init__.py
cypar.egg-info/PKG-INFO
cypar.egg-info/SOURCES.txt
cypar.egg-info/dependency_links.txt
cypar.egg-info/not-zip-safe
cypar.egg-info/top_level.txt