Metadata-Version: 1.0
Name: cypar
Version: 0.1
Summary: Package handling cy-type parameter files
Home-page: http://gitlab.com/cycyustc/cypar
Author: Yang Chen
Author-email: cycyustc@gmail.com
License: CYCY
Platform: UNKNOWN
